hhlGame/__init__.py
hhlGame/g_functions.py
hhlGame/g_obj.py
hhlGame/game_fast_build.py
hhlGame/gameeventloop.py
hhlGame/gamelib.py
hhlGame/gameobj.py
hhlGame/gamescene.py
hhlGame/gametools.py
hhl_game-1.0.1.dist-info/METADATA
hhl_game-1.0.1.dist-info/WHEEL
hhl_game-1.0.1.dist-info/top_level.txt
hhl_game-1.0.1.dist-info/RECORD
